[
  {
    "symbol": "ETHUSDT",
    "timeframe": "5m",
    "direction": "SHORT",
    "entry": 2125.65,
    "dobar_low": 2127.995346,
    "dobar_high": 2132.686038,
    "tps": [
      [
        2121.897447,
        94,
        0.2
      ],
      [
        2119.552101,
        24,
        0.3
      ],
      [
        2116.268617,
        8,
        0.4
      ],
      [
        2111.577925,
        0,
        0.7
      ]
    ],
    "stats": {
      "count": 51,
      "avg_dev": 0.2,
      "deviations": {
        "1": 1,
        "2": 1
      },
      "tp_probs": [
        94,
        24,
        8,
        0
      ],
      "is_valid": true
    },
    "tier": "🟢",
    "stop_loss": 2135.031383,
    "show_dobar": true,
    "chart_message_id": 1298,
    "stat_id": 1
  },
  {
    "symbol": "LINKUSDT",
    "timeframe": "5m",
    "direction": "SHORT",
    "entry": 9.571,
    "dobar_low": 9.585302,
    "dobar_high": 9.613907,
    "tps": [
      [
        9.548116,
        89,
        0.2
      ],
      [
        9.533814,
        26,
        0.4
      ],
      [
        9.513791,
        6,
        0.6
      ],
      [
        9.485187,
        0,
        0.9
      ]
    ],
    "stats": {
      "count": 35,
      "avg_dev": 0.3,
      "deviations": {
        "1": 2
      },
      "tp_probs": [
        89,
        26,
        6,
        0
      ],
      "is_valid": true
    },
    "tier": "🟢",
    "stop_loss": 9.628209,
    "show_dobar": true,
    "chart_message_id": 1299,
    "stat_id": null
  }
]